cunumpy/__init__.py
cunumpy/main.py
cunumpy/xp.py
cunumpy-0.1.dist-info/METADATA
cunumpy-0.1.dist-info/WHEEL
cunumpy-0.1.dist-info/top_level.txt
cunumpy-0.1.dist-info/RECORD
