Metadata-Version: 2.4
Name: cunumpy
Version: 0.1
Summary: Simple wrapper for numpy and cupy. Replace `import numpy as np` with `import cunumpy as xp`.
Author: Max
Project-URL: Source, https://github.com/max-models/cunumpy
Keywords: python
Classifier: Development Status :: 3 - Alpha
Classifier: Programming Language :: Python :: 3 :: Only
Classifier: Programming Language :: Python :: 3.8
Classifier: Programming Language :: Python :: 3.9
Classifier: Programming Language :: Python :: 3.10
Classifier: Programming Language :: Python :: 3.11
Classifier: Programming Language :: Python :: 3.12
Classifier: Programming Language :: Python :: 3.13
Requires-Python: >=3.8
Requires-Dist: numpy
Provides-Extra: dev
Requires-Dist: black[jupyter]; extra == "dev"
Requires-Dist: isort; extra == "dev"
Requires-Dist: cunumpy[docs,test]; extra == "dev"
Provides-Extra: docs
Requires-Dist: ipykernel; extra == "docs"
Requires-Dist: myst-parser; extra == "docs"
Requires-Dist: nbconvert; extra == "docs"
Requires-Dist: nbsphinx; extra == "docs"
Requires-Dist: jupyterlab; extra == "docs"
Requires-Dist: pre-commit; extra == "docs"
Requires-Dist: pyproject-fmt; extra == "docs"
Requires-Dist: sphinx; extra == "docs"
Requires-Dist: sphinx-book-theme; extra == "docs"
Provides-Extra: test
Requires-Dist: coverage; extra == "test"
Requires-Dist: pytest; extra == "test"
